kartverket_tide_api/__init__.py
kartverket_tide_api/tide_api.py
kartverket_tide_api/exceptions/__init__.py
kartverket_tide_api/exceptions/apierrorexception.py
kartverket_tide_api/exceptions/cannotfindelementexception.py
kartverket_tide_api/parsers/__init__.py
kartverket_tide_api/parsers/abstractresponseparser.py
kartverket_tide_api/parsers/locationdataparser.py
kartverket_tide_api/parsers/stationlistparser.py
kartverket_tide_api/tests/TestApiParserIntegration.py
kartverket_tide_api/tests/Testparsers.py
kartverket_tide_api/tests/Testtideapi.py
kartverket_tide_api/tests/__init__.py
kartverket_tide_api/tideobjects/__init__.py
kartverket_tide_api/tideobjects/location.py
kartverket_tide_api/tideobjects/station.py
kartverket_tide_api/tideobjects/waterlevel.py
kartverket_tide_api-1.0.0.dist-info/licenses/LICENCE.TXT
kartverket_tide_api-1.0.0.dist-info/METADATA
kartverket_tide_api-1.0.0.dist-info/WHEEL
kartverket_tide_api-1.0.0.dist-info/top_level.txt
kartverket_tide_api-1.0.0.dist-info/RECORD
