Metadata-Version: 2.4
Name: kartverket_tide_api
Version: 1.0.0
Summary: Unofficial library for the Kartverket tide API
Home-page: https://github.com/matsjp/kartverket_tide_api
Download-URL: https://github.com/matsjp/kartverket_tide_api/archive/refs/tags/v1.0.0.tar.gz
Author: Mats Johan Pedersen
Author-email: Mats Johan Pedersen <matspedersen@protonmail.com>
License: MIT
Project-URL: Homepage, https://github.com/matsjp/kartverket_tide_api
Project-URL: Download, https://github.com/matsjp/kartverket_tide_api/archive/refs/tags/v1.0.0.tar.gz
Project-URL: Bug Tracker, https://github.com/matsjp/kartverket_tide_api/issues
Keywords: kartverket,tide,api
Classifier: Development Status :: 3 - Alpha
Classifier: Intended Audience :: Developers
Classifier: Topic :: Software Development :: Build Tools
Classifier: License :: OSI Approved :: MIT License
Classifier: Programming Language :: Python :: 3.6
Classifier: Programming Language :: Python :: 3.7
Classifier: Programming Language :: Python :: 3.8
Classifier: Programming Language :: Python :: 3.9
Classifier: Programming Language :: Python :: 3.10
Requires-Python: >=3.6
License-File: LICENCE.TXT
Requires-Dist: requests
Requires-Dist: vcrpy
Dynamic: author
Dynamic: download-url
Dynamic: home-page
Dynamic: license-file
Dynamic: requires-python
